tinyfilemanager/__init__.py
tinyfilemanager/constants.py
tinyfilemanager/error.py
tinyfilemanager/tinyfilemanager.py
tinyfilemanager/version.py
tinyfilemanager-0.2.0.dist-info/LICENSE
tinyfilemanager-0.2.0.dist-info/WHEEL
tinyfilemanager-0.2.0.dist-info/METADATA
tinyfilemanager-0.2.0.dist-info/RECORD
